oxflags/__init__.py
oxflags/main.py
oxflags-0.0.6.dist-info/METADATA
oxflags-0.0.6.dist-info/WHEEL
oxflags-0.0.6.dist-info/top_level.txt
oxflags-0.0.6.dist-info/RECORD
