Metadata-Version: 2.1
Name: oxflags
Version: 0.0.6
Summary: A Handy Package to Parse Command-Line Arguments
Author: 0x68616469
Keywords: flags,command-line,arguments
Classifier: Development Status :: 4 - Beta
Classifier: Intended Audience :: Developers
Classifier: Programming Language :: Python :: 3
Classifier: Operating System :: Unix
Classifier: Operating System :: MacOS :: MacOS X
Classifier: Operating System :: Microsoft :: Windows
Requires-Dist: oxansi
Requires-Dist: oxtables
